fs_encrypted/__init__.py
fs_encrypted/encrypted_fs.py
fs_encrypted/opener.py
fs_encrypted/pathlike.py
fs_encrypted-1.0.dist-info/LICENSE.md
fs_encrypted-1.0.dist-info/METADATA
fs_encrypted-1.0.dist-info/WHEEL
fs_encrypted-1.0.dist-info/RECORD
