Metadata-Version: 2.1
Name: fs-encrypted
Version: 1.0
Summary: An encrypted filesystem for python using PYFilesystem2
Home-page: https://github.com/thevgergroup/fs-encrypted
License: MIT
Keywords: filesystem,encryption,pyfilesystem2
Author: patrick o'leary
Author-email: pjaol@pjaol.com
Requires-Python: >=3.9,<4.0
Classifier: License :: OSI Approved :: MIT License
Classifier: Programming Language :: Python :: 3
Classifier: Programming Language :: Python :: 3.9
Classifier: Programming Language :: Python :: 3.10
Classifier: Programming Language :: Python :: 3.11
Classifier: Programming Language :: Python :: 3.12
Classifier: Topic :: Security
Classifier: Topic :: Security :: Cryptography
Classifier: Topic :: System :: Filesystems
Requires-Dist: cryptography (>=41.0.7,<44.0.0)
Requires-Dist: fs (>=2.4.16,<3.0.0)
Project-URL: Repository, https://github.com/thevgergroup/fs-encrypted.git
